Metadata-Version: 2.1
Name: ChromaticPrint
Version: 0.1.5
Summary: A library for printing colored text in the terminal
Home-page: https://github.com/INeddHelp/Colors-python-library
Author: INeddHelp
Author-email: ineddhelpgithub@gmail.com
